{
  "elo": {
    "Argentina": 2145.0,
    "France": 2105.0,
    "Spain": 2085.0,
    "England": 2050.0,
    "Brazil": 2040.0,
    "Portugal": 2010.0,
    "Netherlands": 2000.0,
    "Germany": 1965.0,
    "Belgium": 1945.0,
    "Croatia": 1935.0,
    "Italy": 1925.0,
    "Uruguay": 1915.0,
    "Colombia": 1900.0,
    "Morocco": 1885.0,
    "Switzerland": 1875.0,
    "Denmark": 1865.0,
    "Japan": 1835.0,
    "United States": 1831.8,
    "Mexico": 1820.2,
    "Senegal": 1810.0,
    "Ecuador": 1795.0,
    "Austria": 1790.0,
    "Serbia": 1785.0,
    "Ukraine": 1780.0,
    "Korea Republic": 1765.0,
    "South Korea": 1777.1,
    "Iran": 1760.0,
    "Australia": 1745.0,
    "Canada": 1735.3,
    "Poland": 1740.0,
    "Sweden": 1735.0,
    "Wales": 1730.0,
    "Norway": 1725.0,
    "Turkey": 1720.0,
    "Egypt": 1710.0,
    "Nigeria": 1705.0,
    "Peru": 1700.0,
    "Ivory Coast": 1695.0,
    "Cote d'Ivoire": 1695.0,
    "Tunisia": 1685.0,
    "Algeria": 1685.0,
    "Paraguay": 1658.2,
    "Czech Republic": 1675.0,
    "Chile": 1670.0,
    "Cameroon": 1665.0,
    "Scotland": 1660.0,
    "Ghana": 1655.0,
    "Mali": 1650.0,
    "Greece": 1645.0,
    "Costa Rica": 1635.0,
    "Qatar": 1630.0,
    "Saudi Arabia": 1625.0,
    "Panama": 1615.0,
    "Jamaica": 1600.0,
    "South Africa": 1584.8,
    "New Zealand": 1545.0,
    "Honduras": 1535.0,
    "Uzbekistan": 1530.0,
    "Jordan": 1520.0,
    "Cape Verde": 1515.0,
    "Curacao": 1490.0,
    "Haiti": 1470.0,
    "Czechia": 1607.9,
    "Bosnia-Herzegovina": 1629.7
  },
  "processed_ids": [
    "760414",
    "760415",
    "760416",
    "760417"
  ]
}